BL_Python/GitHub/__init__.py
BL_Python/GitHub/api.py
BL_Python.GitHub-0.2.0.dist-info/LICENSE.md
BL_Python.GitHub-0.2.0.dist-info/METADATA
BL_Python.GitHub-0.2.0.dist-info/WHEEL
BL_Python.GitHub-0.2.0.dist-info/top_level.txt
BL_Python.GitHub-0.2.0.dist-info/RECORD
