Metadata-Version: 2.1
Name: BL_Python.GitHub
Version: 0.2.0
Summary: Libraries for working with the GitHub API in Boutros Lab.
Author-email: Aaron Holmes <aholmes@mednet.ucla.edu>
Classifier: Programming Language :: Python :: 3
Classifier: License :: OSI Approved :: GNU General Public License (GPL)
Classifier: Operating System :: OS Independent
Requires-Python: >=3.10
License-File: LICENSE.md
Requires-Dist: PyGithub
Provides-Extra: dev-dependencies
Requires-Dist: pytest ; extra == 'dev-dependencies'
Requires-Dist: pytest-mock ; extra == 'dev-dependencies'
Requires-Dist: mock ; extra == 'dev-dependencies'
